{
  "update_time": "2026-04-27 15:55:10",
  "school_id": "1038",
  "school_name": "重庆文理学院",
  "jobrateyear": "2023",
  "jobrate": {
    "job": {
      "1": "95.44"
    },
    "postgraduate": {
      "1": "11.36"
    },
    "abroad": {
      "1": "0.72"
    }
  },
  "province": [
    {
      "id": "23045",
      "school_id": "1038",
      "province": "北京市",
      "rate": "1.13",
      "num": "0",
      "sort": "113",
      "update_id": "2096",
      "update_time": "2024-09-26 14:50:31",
      "year": "2023",
      "province_name": "北京市"
    },
    {
      "id": "23044",
      "school_id": "1038",
      "province": "陕西省",
      "rate": "1.17",
      "num": "0",
      "sort": "117",
      "update_id": "2096",
      "update_time": "2024-09-26 14:50:31",
      "year": "2023",
      "province_name": "陕西省"
    },
    {
      "id": "23043",
      "school_id": "1038",
      "province": "贵州省",
      "rate": "1.31",
      "num": "0",
      "sort": "131",
      "update_id": "2096",
      "update_time": "2024-09-26 14:50:31",
      "year": "2023",
      "province_name": "贵州省"
    },
    {
      "id": "23042",
      "school_id": "1038",
      "province": "上海市",
      "rate": "1.35",
      "num": "0",
      "sort": "135",
      "update_id": "2096",
      "update_time": "2024-09-26 14:50:31",
      "year": "2023",
      "province_name": "上海市"
    },
    {
      "id": "23041",
      "school_id": "1038",
      "province": "新疆维吾尔自治区",
      "rate": "1.60",
      "num": "0",
      "sort": "160",
      "update_id": "2096",
      "update_time": "2024-09-26 14:50:31",
      "year": "2023",
      "province_name": "新疆维吾尔自治区"
    },
    {
      "id": "23040",
      "school_id": "1038",
      "province": "江苏省",
      "rate": "1.84",
      "num": "0",
      "sort": "184",
      "update_id": "2096",
      "update_time": "2024-09-26 14:50:31",
      "year": "2023",
      "province_name": "江苏省"
    },
    {
      "id": "23039",
      "school_id": "1038",
      "province": "广东省",
      "rate": "4.25",
      "num": "0",
      "sort": "425",
      "update_id": "2096",
      "update_time": "2024-09-26 14:50:31",
      "year": "2023",
      "province_name": "广东省"
    },
    {
      "id": "23038",
      "school_id": "1038",
      "province": "浙江省",
      "rate": "4.87",
      "num": "0",
      "sort": "487",
      "update_id": "2096",
      "update_time": "2024-09-26 14:50:31",
      "year": "2023",
      "province_name": "浙江省"
    },
    {
      "id": "23037",
      "school_id": "1038",
      "province": "四川省",
      "rate": "7.83",
      "num": "0",
      "sort": "783",
      "update_id": "2096",
      "update_time": "2024-09-26 14:50:31",
      "year": "2023",
      "province_name": "四川省"
    },
    {
      "id": "23046",
      "school_id": "1038",
      "province": "其他省区市",
      "rate": "10.10",
      "num": "0",
      "sort": "1010",
      "update_id": "2096",
      "update_time": "2024-09-26 14:50:31",
      "year": "2023",
      "province_name": "其他省区市"
    },
    {
      "id": "23036",
      "school_id": "1038",
      "province": "重庆市",
      "rate": "64.55",
      "num": "0",
      "sort": "6455",
      "update_id": "2096",
      "update_time": "2024-09-26 14:50:31",
      "year": "2023",
      "province_name": "重庆市"
    }
  ],
  "attr": {
    "其他企业": "76.94",
    "中初教育单位": "8.25",
    "国有企业": "7.62",
    "三资企业": "2.71",
    "其他事业单位": "2.56",
    "机关": "1.21",
    "医疗卫生单位": "0.39",
    "高等教育单位": "0.26",
    "农村建制村": "0.02",
    "科研设计单位": "0.02",
    "城镇社区": "0.02"
  },
  "company": {},
  "gradute": [
    {
      "id": "2016",
      "school_id": "1038",
      "female_num": "3361",
      "men_num": "2599",
      "men_rate": "43.61",
      "female_rate": "56.39",
      "update_id": "2096",
      "update_time": "2024-09-26 14:49:25",
      "year": "2023"
    }
  ],
  "remark": "",
  "salary": {
    "6": "8700"
  }
}