{
  "update_time": "2026-04-27 16:01:20",
  "school_id": "1778",
  "school_name": "浙江警官职业学院",
  "jobrateyear": "2024",
  "jobrate": {
    "job": {
      "1": "99.61"
    },
    "postgraduate": {
      "1": "29.98"
    },
    "abroad": {
      "1": "0.00"
    }
  },
  "province": [
    {
      "id": "32727",
      "school_id": "1778",
      "province": "省外",
      "rate": "13.54",
      "num": "0",
      "sort": "1354",
      "update_id": "2096",
      "update_time": "2025-12-02 10:36:25",
      "year": "2024",
      "province_name": "省外"
    },
    {
      "id": "32726",
      "school_id": "1778",
      "province": "浙江",
      "rate": "86.46",
      "num": "0",
      "sort": "8646",
      "update_id": "2096",
      "update_time": "2025-12-02 10:36:25",
      "year": "2024",
      "province_name": "浙江"
    }
  ],
  "attr": {
    "机关": "62.62",
    "其他企业": "16.71",
    "其他": "15.07",
    "个体工商户": "4.09",
    "民营企业": "0.82",
    "高等教育单位": "0.35",
    "其他事业单位": "0.23",
    "中初教育单位": "0.11"
  },
  "company": {},
  "gradute": [
    {
      "id": "2810",
      "school_id": "1778",
      "female_num": "304",
      "men_num": "980",
      "men_rate": "76.32",
      "female_rate": "23.68",
      "update_id": "2096",
      "update_time": "2025-12-02 10:31:31",
      "year": "2024"
    }
  ],
  "remark": "",
  "salary": {
    "6": "9400"
  }
}