{
  "update_time": "2026-05-01 07:01:51",
  "school_id": "3052",
  "school_name": "哈尔滨幼儿师范高等专科学校",
  "jobrateyear": "2024",
  "jobrate": {
    "job": {
      "1": "90.83"
    },
    "postgraduate": {
      "1": "33.62"
    },
    "abroad": {
      "1": "0.14"
    }
  },
  "province": [
    {
      "id": "32166",
      "school_id": "3052",
      "province": "青海省",
      "rate": "0.14",
      "num": "1",
      "sort": "357",
      "update_id": "2156",
      "update_time": "2025-12-01 14:36:29",
      "year": "2024",
      "province_name": "青海省"
    },
    {
      "id": "32165",
      "school_id": "3052",
      "province": "内蒙古自治区",
      "rate": "0.14",
      "num": "1",
      "sort": "358",
      "update_id": "2156",
      "update_time": "2025-12-01 14:36:29",
      "year": "2024",
      "province_name": "内蒙古自治区"
    },
    {
      "id": "32164",
      "school_id": "3052",
      "province": "天津市",
      "rate": "0.14",
      "num": "1",
      "sort": "359",
      "update_id": "2156",
      "update_time": "2025-12-01 14:36:29",
      "year": "2024",
      "province_name": "天津市"
    },
    {
      "id": "32163",
      "school_id": "3052",
      "province": "西藏自治区",
      "rate": "0.14",
      "num": "1",
      "sort": "360",
      "update_id": "2156",
      "update_time": "2025-12-01 14:36:29",
      "year": "2024",
      "province_name": "西藏自治区"
    },
    {
      "id": "32162",
      "school_id": "3052",
      "province": "广西壮族自治区",
      "rate": "0.14",
      "num": "1",
      "sort": "361",
      "update_id": "2156",
      "update_time": "2025-12-01 14:36:29",
      "year": "2024",
      "province_name": "广西壮族自治区"
    },
    {
      "id": "32161",
      "school_id": "3052",
      "province": "新疆维吾尔自治区",
      "rate": "0.14",
      "num": "1",
      "sort": "362",
      "update_id": "2156",
      "update_time": "2025-12-01 14:36:29",
      "year": "2024",
      "province_name": "新疆维吾尔自治区"
    },
    {
      "id": "32160",
      "school_id": "3052",
      "province": "山西省",
      "rate": "0.27",
      "num": "2",
      "sort": "363",
      "update_id": "2156",
      "update_time": "2025-12-01 14:36:29",
      "year": "2024",
      "province_name": "山西省"
    },
    {
      "id": "32159",
      "school_id": "3052",
      "province": "海南省",
      "rate": "0.27",
      "num": "2",
      "sort": "364",
      "update_id": "2156",
      "update_time": "2025-12-01 14:36:29",
      "year": "2024",
      "province_name": "海南省"
    },
    {
      "id": "32158",
      "school_id": "3052",
      "province": "江苏省",
      "rate": "0.27",
      "num": "2",
      "sort": "365",
      "update_id": "2156",
      "update_time": "2025-12-01 14:36:29",
      "year": "2024",
      "province_name": "江苏省"
    },
    {
      "id": "32157",
      "school_id": "3052",
      "province": "福建省",
      "rate": "0.41",
      "num": "3",
      "sort": "366",
      "update_id": "2156",
      "update_time": "2025-12-01 14:36:29",
      "year": "2024",
      "province_name": "福建省"
    },
    {
      "id": "32156",
      "school_id": "3052",
      "province": "云南省",
      "rate": "0.41",
      "num": "3",
      "sort": "367",
      "update_id": "2156",
      "update_time": "2025-12-01 14:36:29",
      "year": "2024",
      "province_name": "云南省"
    },
    {
      "id": "32155",
      "school_id": "3052",
      "province": "上海市",
      "rate": "0.54",
      "num": "4",
      "sort": "368",
      "update_id": "2156",
      "update_time": "2025-12-01 14:36:29",
      "year": "2024",
      "province_name": "上海市"
    },
    {
      "id": "32154",
      "school_id": "3052",
      "province": "陕西省",
      "rate": "0.82",
      "num": "6",
      "sort": "369",
      "update_id": "2156",
      "update_time": "2025-12-01 14:36:29",
      "year": "2024",
      "province_name": "陕西省"
    },
    {
      "id": "32153",
      "school_id": "3052",
      "province": "山东省",
      "rate": "0.95",
      "num": "7",
      "sort": "370",
      "update_id": "2156",
      "update_time": "2025-12-01 14:36:29",
      "year": "2024",
      "province_name": "山东省"
    },
    {
      "id": "32152",
      "school_id": "3052",
      "province": "江西省",
      "rate": "1.09",
      "num": "8",
      "sort": "371",
      "update_id": "2156",
      "update_time": "2025-12-01 14:36:29",
      "year": "2024",
      "province_name": "江西省"
    },
    {
      "id": "32151",
      "school_id": "3052",
      "province": "湖南省",
      "rate": "1.22",
      "num": "9",
      "sort": "372",
      "update_id": "2156",
      "update_time": "2025-12-01 14:36:29",
      "year": "2024",
      "province_name": "湖南省"
    },
    {
      "id": "32150",
      "school_id": "3052",
      "province": "甘肃省",
      "rate": "1.22",
      "num": "9",
      "sort": "373",
      "update_id": "2156",
      "update_time": "2025-12-01 14:36:29",
      "year": "2024",
      "province_name": "甘肃省"
    },
    {
      "id": "32149",
      "school_id": "3052",
      "province": "四川省",
      "rate": "1.49",
      "num": "11",
      "sort": "374",
      "update_id": "2156",
      "update_time": "2025-12-01 14:36:29",
      "year": "2024",
      "province_name": "四川省"
    },
    {
      "id": "32148",
      "school_id": "3052",
      "province": "辽宁省",
      "rate": "2.04",
      "num": "15",
      "sort": "375",
      "update_id": "2156",
      "update_time": "2025-12-01 14:36:29",
      "year": "2024",
      "province_name": "辽宁省"
    },
    {
      "id": "32147",
      "school_id": "3052",
      "province": "重庆市",
      "rate": "2.31",
      "num": "17",
      "sort": "376",
      "update_id": "2156",
      "update_time": "2025-12-01 14:36:29",
      "year": "2024",
      "province_name": "重庆市"
    },
    {
      "id": "32146",
      "school_id": "3052",
      "province": "浙江省",
      "rate": "2.45",
      "num": "18",
      "sort": "377",
      "update_id": "2156",
      "update_time": "2025-12-01 14:36:29",
      "year": "2024",
      "province_name": "浙江省"
    },
    {
      "id": "32145",
      "school_id": "3052",
      "province": "河北省",
      "rate": "2.45",
      "num": "18",
      "sort": "378",
      "update_id": "2156",
      "update_time": "2025-12-01 14:36:29",
      "year": "2024",
      "province_name": "河北省"
    },
    {
      "id": "32144",
      "school_id": "3052",
      "province": "广东省",
      "rate": "2.85",
      "num": "21",
      "sort": "379",
      "update_id": "2156",
      "update_time": "2025-12-01 14:36:29",
      "year": "2024",
      "province_name": "广东省"
    },
    {
      "id": "32143",
      "school_id": "3052",
      "province": "北京市",
      "rate": "2.85",
      "num": "21",
      "sort": "380",
      "update_id": "2156",
      "update_time": "2025-12-01 14:36:29",
      "year": "2024",
      "province_name": "北京市"
    },
    {
      "id": "32142",
      "school_id": "3052",
      "province": "贵州省",
      "rate": "2.99",
      "num": "22",
      "sort": "381",
      "update_id": "2156",
      "update_time": "2025-12-01 14:36:29",
      "year": "2024",
      "province_name": "贵州省"
    },
    {
      "id": "32141",
      "school_id": "3052",
      "province": "吉林省",
      "rate": "4.62",
      "num": "34",
      "sort": "382",
      "update_id": "2156",
      "update_time": "2025-12-01 14:36:29",
      "year": "2024",
      "province_name": "吉林省"
    },
    {
      "id": "32140",
      "school_id": "3052",
      "province": "河南省",
      "rate": "5.30",
      "num": "39",
      "sort": "383",
      "update_id": "2156",
      "update_time": "2025-12-01 14:36:29",
      "year": "2024",
      "province_name": "河南省"
    },
    {
      "id": "32139",
      "school_id": "3052",
      "province": "黑龙江省",
      "rate": "62.36",
      "num": "459",
      "sort": "384",
      "update_id": "2156",
      "update_time": "2025-12-01 14:36:29",
      "year": "2024",
      "province_name": "黑龙江省"
    }
  ],
  "attr": {
    "其他企业 (含民营企业等)": "42.80",
    "其他 (含社会组织等)": "30.30",
    "个体工商户": "16.98",
    "中初教育单位": "7.20",
    "其他事业单位": "1.49",
    "国有企业": "0.95",
    "机关": "0.27"
  },
  "company": {},
  "gradute": [
    {
      "id": "2764",
      "school_id": "3052",
      "female_num": "1281",
      "men_num": "126",
      "men_rate": "8.96",
      "female_rate": "91.04",
      "update_id": "2156",
      "update_time": "2025-12-01 14:34:59",
      "year": "2024"
    }
  ],
  "remark": "",
  "salary": {
    "6": "7000"
  }
}