{
  "update_time": "2026-04-27 16:12:48",
  "school_id": "3161",
  "school_name": "辽宁特殊教育师范高等专科学校",
  "jobrateyear": "2024",
  "jobrate": {
    "job": {
      "1": "91.38"
    },
    "postgraduate": {
      "1": "11.93"
    },
    "abroad": {
      "1": "0.00"
    }
  },
  "province": [
    {
      "id": "27894",
      "school_id": "3161",
      "province": "省外",
      "rate": "8.47",
      "num": "0",
      "sort": "847",
      "update_id": "2096",
      "update_time": "2025-07-09 17:59:54",
      "year": "2024",
      "province_name": "省外"
    },
    {
      "id": "27893",
      "school_id": "3161",
      "province": "辽宁省内",
      "rate": "91.53",
      "num": "0",
      "sort": "9153",
      "update_id": "2096",
      "update_time": "2025-07-09 17:59:23",
      "year": "2024",
      "province_name": "辽宁省内"
    }
  ],
  "attr": {
    "其他企业（含民营企业等）": "66.10",
    "个体工商户": "29.38",
    "其他事业单位": "2.54",
    "机关": "1.13",
    "医疗卫生单位": "0.28",
    "社会组织、国际组织等": "0.28",
    "国有企业": "0.28"
  },
  "company": {},
  "gradute": [
    {
      "id": "2380",
      "school_id": "3161",
      "female_num": "382",
      "men_num": "163",
      "men_rate": "29.91",
      "female_rate": "70.09",
      "update_id": "2096",
      "update_time": "2025-07-09 17:57:48",
      "year": "2024"
    }
  ],
  "remark": "",
  "salary": {
    "6": "8100"
  }
}