{
  "update_time": "2026-04-27 15:48:18",
  "school_id": "351",
  "school_name": "西安建筑科技大学",
  "jobrateyear": "2023",
  "jobrate": {
    "job": {
      "1": "88.96"
    },
    "postgraduate": {
      "1": "28.92"
    },
    "abroad": {
      "1": "6.51"
    }
  },
  "province": [
    {
      "id": "17908",
      "school_id": "351",
      "province": "国外",
      "rate": "0.14",
      "num": "3",
      "sort": "3",
      "update_id": "2004",
      "update_time": "2024-06-13 16:10:05",
      "year": "2023",
      "province_name": "国外"
    },
    {
      "id": "17906",
      "school_id": "351",
      "province": "黑龙江省",
      "rate": "0.14",
      "num": "3",
      "sort": "3",
      "update_id": "2004",
      "update_time": "2024-06-13 16:10:05",
      "year": "2023",
      "province_name": "黑龙江省"
    },
    {
      "id": "17905",
      "school_id": "351",
      "province": "青海省",
      "rate": "0.14",
      "num": "3",
      "sort": "3",
      "update_id": "2004",
      "update_time": "2024-06-13 16:10:05",
      "year": "2023",
      "province_name": "青海省"
    },
    {
      "id": "17904",
      "school_id": "351",
      "province": "海南省",
      "rate": "0.18",
      "num": "4",
      "sort": "4",
      "update_id": "2004",
      "update_time": "2024-06-13 16:10:05",
      "year": "2023",
      "province_name": "海南省"
    },
    {
      "id": "17897",
      "school_id": "351",
      "province": "江西省",
      "rate": "0.23",
      "num": "5",
      "sort": "5",
      "update_id": "2004",
      "update_time": "2024-06-13 16:10:05",
      "year": "2023",
      "province_name": "江西省"
    },
    {
      "id": "17907",
      "school_id": "351",
      "province": "广西壮族自治区",
      "rate": "0.32",
      "num": "7",
      "sort": "7",
      "update_id": "2004",
      "update_time": "2024-06-13 16:10:05",
      "year": "2023",
      "province_name": "广西壮族自治区"
    },
    {
      "id": "17901",
      "school_id": "351",
      "province": "宁夏回族自治区",
      "rate": "0.37",
      "num": "8",
      "sort": "8",
      "update_id": "2004",
      "update_time": "2024-06-13 16:10:05",
      "year": "2023",
      "province_name": "宁夏回族自治区"
    },
    {
      "id": "17900",
      "school_id": "351",
      "province": "内蒙古自治区",
      "rate": "0.37",
      "num": "8",
      "sort": "8",
      "update_id": "2004",
      "update_time": "2024-06-13 16:10:05",
      "year": "2023",
      "province_name": "内蒙古自治区"
    },
    {
      "id": "17898",
      "school_id": "351",
      "province": "天津市",
      "rate": "0.37",
      "num": "8",
      "sort": "8",
      "update_id": "2004",
      "update_time": "2024-06-13 16:10:05",
      "year": "2023",
      "province_name": "天津市"
    },
    {
      "id": "17892",
      "school_id": "351",
      "province": "甘肃省",
      "rate": "0.42",
      "num": "9",
      "sort": "9",
      "update_id": "2004",
      "update_time": "2024-06-13 16:10:05",
      "year": "2023",
      "province_name": "甘肃省"
    },
    {
      "id": "17903",
      "school_id": "351",
      "province": "贵州省",
      "rate": "0.46",
      "num": "10",
      "sort": "10",
      "update_id": "2004",
      "update_time": "2024-06-13 16:10:05",
      "year": "2023",
      "province_name": "贵州省"
    },
    {
      "id": "17893",
      "school_id": "351",
      "province": "山西省",
      "rate": "0.46",
      "num": "10",
      "sort": "10",
      "update_id": "2004",
      "update_time": "2024-06-13 16:10:05",
      "year": "2023",
      "province_name": "山西省"
    },
    {
      "id": "17902",
      "school_id": "351",
      "province": "云南省",
      "rate": "0.51",
      "num": "11",
      "sort": "11",
      "update_id": "2004",
      "update_time": "2024-06-13 16:10:05",
      "year": "2023",
      "province_name": "云南省"
    },
    {
      "id": "17896",
      "school_id": "351",
      "province": "福建省",
      "rate": "0.60",
      "num": "13",
      "sort": "13",
      "update_id": "2004",
      "update_time": "2024-06-13 16:10:05",
      "year": "2023",
      "province_name": "福建省"
    },
    {
      "id": "17899",
      "school_id": "351",
      "province": "辽宁省",
      "rate": "0.60",
      "num": "13",
      "sort": "13",
      "update_id": "2004",
      "update_time": "2024-06-13 16:10:05",
      "year": "2023",
      "province_name": "辽宁省"
    },
    {
      "id": "17894",
      "school_id": "351",
      "province": "重庆市",
      "rate": "0.69",
      "num": "15",
      "sort": "15",
      "update_id": "2004",
      "update_time": "2024-06-13 16:10:05",
      "year": "2023",
      "province_name": "重庆市"
    },
    {
      "id": "17895",
      "school_id": "351",
      "province": "新疆维吾尔自治区",
      "rate": "0.74",
      "num": "16",
      "sort": "16",
      "update_id": "2004",
      "update_time": "2024-06-13 16:10:05",
      "year": "2023",
      "province_name": "新疆维吾尔自治区"
    },
    {
      "id": "17891",
      "school_id": "351",
      "province": "河北省",
      "rate": "0.88",
      "num": "19",
      "sort": "19",
      "update_id": "2004",
      "update_time": "2024-06-13 16:10:05",
      "year": "2023",
      "province_name": "河北省"
    },
    {
      "id": "17888",
      "school_id": "351",
      "province": "河南省",
      "rate": "0.92",
      "num": "20",
      "sort": "20",
      "update_id": "2004",
      "update_time": "2024-06-13 16:10:05",
      "year": "2023",
      "province_name": "河南省"
    },
    {
      "id": "17890",
      "school_id": "351",
      "province": "安徽省",
      "rate": "1.16",
      "num": "25",
      "sort": "25",
      "update_id": "2004",
      "update_time": "2024-06-13 16:10:05",
      "year": "2023",
      "province_name": "安徽省"
    },
    {
      "id": "17882",
      "school_id": "351",
      "province": "山东省",
      "rate": "1.99",
      "num": "43",
      "sort": "43",
      "update_id": "2004",
      "update_time": "2024-06-13 16:10:05",
      "year": "2023",
      "province_name": "山东省"
    },
    {
      "id": "17889",
      "school_id": "351",
      "province": "湖南省",
      "rate": "2.45",
      "num": "53",
      "sort": "53",
      "update_id": "2004",
      "update_time": "2024-06-13 16:10:05",
      "year": "2023",
      "province_name": "湖南省"
    },
    {
      "id": "17885",
      "school_id": "351",
      "province": "四川省",
      "rate": "2.54",
      "num": "55",
      "sort": "55",
      "update_id": "2004",
      "update_time": "2024-06-13 16:10:05",
      "year": "2023",
      "province_name": "四川省"
    },
    {
      "id": "17887",
      "school_id": "351",
      "province": "浙江省",
      "rate": "2.59",
      "num": "56",
      "sort": "56",
      "update_id": "2004",
      "update_time": "2024-06-13 16:10:05",
      "year": "2023",
      "province_name": "浙江省"
    },
    {
      "id": "17886",
      "school_id": "351",
      "province": "湖北省",
      "rate": "2.87",
      "num": "62",
      "sort": "62",
      "update_id": "2004",
      "update_time": "2024-06-13 16:10:05",
      "year": "2023",
      "province_name": "湖北省"
    },
    {
      "id": "17883",
      "school_id": "351",
      "province": "江苏省",
      "rate": "3.88",
      "num": "84",
      "sort": "84",
      "update_id": "2004",
      "update_time": "2024-06-13 16:10:05",
      "year": "2023",
      "province_name": "江苏省"
    },
    {
      "id": "17884",
      "school_id": "351",
      "province": "上海市",
      "rate": "4.07",
      "num": "88",
      "sort": "88",
      "update_id": "2004",
      "update_time": "2024-06-13 16:10:05",
      "year": "2023",
      "province_name": "上海市"
    },
    {
      "id": "17881",
      "school_id": "351",
      "province": "北京市",
      "rate": "4.99",
      "num": "108",
      "sort": "108",
      "update_id": "2004",
      "update_time": "2024-06-13 16:10:05",
      "year": "2023",
      "province_name": "北京市"
    },
    {
      "id": "17880",
      "school_id": "351",
      "province": "广东省",
      "rate": "6.61",
      "num": "143",
      "sort": "143",
      "update_id": "2004",
      "update_time": "2024-06-13 16:10:05",
      "year": "2023",
      "province_name": "广东省"
    },
    {
      "id": "17879",
      "school_id": "351",
      "province": "陕西省",
      "rate": "58.30",
      "num": "1261",
      "sort": "1261",
      "update_id": "2004",
      "update_time": "2024-06-13 16:10:05",
      "year": "2023",
      "province_name": "陕西省"
    }
  ],
  "attr": {
    "其他企业": "50.62",
    "国有企业": "40.55",
    "机关": "2.64",
    "三资企业": "2.17",
    "科研设计单位": "1.62",
    "其他事业单位": "1.02",
    "中初教育单位": "0.79",
    "高等教育单位": "0.32",
    "医疗卫生单位": "0.23",
    "城镇社区": "0.05"
  },
  "company": {
    "中国建筑集团有限公司": "497",
    "比亚迪股份有限公司": "136",
    "陕西建工控股集团有限公司": "109",
    "隆基绿能科技股份有限公司": "100",
    "中国铁道建筑集团有限公司": "59",
    "中国铁路工程集团有限公司": "58",
    "中国电力建设集团有限公司": "55",
    "中国交通建设集团有限公司": "49",
    "国家电力投资集团有限公司": "38",
    "国家电网有限公司": "30",
    "潍柴动力股份有限公司": "24",
    "浙江华友钴业股份有限公司": "22",
    "中国能源建设集团有限公司": "20",
    "中国宝武钢铁集团有限公司": "20",
    "中国核工业集团有限公司": "19",
    "中国航空工业集团有限公司": "18",
    "中国建材集团有限公司": "16",
    "特变电工股份有限公司": "13",
    "中国保利集团有限公司": "11",
    "龙湖集团控股有限公司": "11",
    "中国中车集团有限公司": "9",
    "中国移动通信集团有限公司": "9",
    "中国船舶集团有限公司": "8",
    "中国建设银行股份有限公司": "8",
    "陕西煤业化工集团有限责任公司": "8",
    "中国石油天然气集团有限公司": "8",
    "中国邮政集团有限公司": "7",
    "中粮集团有限公司": "7",
    "中国机械工业集团有限公司": "7",
    "中国石油化工集团有限公司": "7",
    "奇瑞控股集团有限公司": "6",
    "中国广核电力股份有限公司": "6",
    "中国农业银行股份有限公司": "5",
    "北京建龙重工集团有限公司": "5",
    "美的集团股份有限公司": "5",
    "紫金矿业集团股份有限公司": "5",
    "海尔智家股份有限公司": "5",
    "中国中信集团有限公司": "5",
    "中国工商银行股份有限公司": "5",
    "招商银行股份有限公司": "5",
    "上海建工集团股份有限公司": "5"
  },
  "gradute": [
    {
      "id": "1641",
      "school_id": "351",
      "female_num": "1959",
      "men_num": "2744",
      "men_rate": "58.35",
      "female_rate": "41.65",
      "update_id": "2004",
      "update_time": "2024-06-13 16:10:41",
      "year": "2023"
    }
  ],
  "remark": "",
  "salary": {
    "6": "11200"
  }
}