{
  "update_time": "2026-04-27 15:54:18",
  "school_id": "953",
  "school_name": "江西航空职业技术学院",
  "jobrateyear": "2023",
  "jobrate": {
    "job": {
      "1": "84.50"
    },
    "postgraduate": {
      "1": "11.43"
    },
    "abroad": {
      "1": "0.00"
    }
  },
  "province": [
    {
      "id": "13858",
      "school_id": "953",
      "province": "一线城市",
      "rate": "12.00",
      "num": "323",
      "sort": "323",
      "update_id": "1988",
      "update_time": "2024-04-28 18:18:15",
      "year": "2023",
      "province_name": "一线城市"
    },
    {
      "id": "13859",
      "school_id": "953",
      "province": "二线城市",
      "rate": "88.00",
      "num": "2267",
      "sort": "2267",
      "update_id": "1988",
      "update_time": "2024-04-28 18:18:32",
      "year": "2023",
      "province_name": "二线城市"
    }
  ],
  "attr": {
    "其他": "50.08",
    "三资及民营企业": "31.43",
    "国有企业": "6.72",
    "机关及事业单位": "6.10",
    "科研设计及服务": "5.29",
    "城镇社区": "0.27",
    "农村建制": "0.12"
  },
  "company": {
    "上海飞机制造有限公司": "36",
    "江西洪都航空工业集团有限责任公司": "28",
    "厦门太古飞机工程有限公司": "21",
    "上海国际主题乐园有限公司": "8"
  },
  "gradute": [
    {
      "id": "1350",
      "school_id": "953",
      "female_num": "263",
      "men_num": "2802",
      "men_rate": "91.42",
      "female_rate": "8.58",
      "update_id": "1988",
      "update_time": "2024-04-28 18:17:26",
      "year": "2023"
    }
  ],
  "remark": "",
  "salary": {
    "6": "8900"
  }
}